deviaTE/__init__.py
deviaTE/analyse.py
deviaTE/config.py
deviaTE/deviate.py
deviaTE/mapping.py
deviaTE/paf.py
deviaTE/plot.py
deviaTE/reference.py
deviaTE/utils.py
deviate-2.2.3.dist-info/METADATA
deviate-2.2.3.dist-info/WHEEL
deviate-2.2.3.dist-info/entry_points.txt
deviate-2.2.3.dist-info/licenses/LICENSE
deviate-2.2.3.dist-info/RECORD
