Metadata-Version: 2.4
Name: deviaTE
Version: 2.2.3
Summary: Python tool for the analysis and visualization of mobile genetic elements
Project-URL: homepage, https://github.com/W-L/deviaTE
License-File: LICENSE
Requires-Python: >=3.12
Requires-Dist: gffutils~=0.13
Requires-Dist: mappy~=2.28
Requires-Dist: numpy~=2.2.2
Requires-Dist: pandas~=2.2
Requires-Dist: plotnine~=0.14
Requires-Dist: rapidgzip~=0.14
Requires-Dist: requests~=2.32
Provides-Extra: dev
Requires-Dist: pytest-cov~=6.0.0; extra == 'dev'
Requires-Dist: pytest~=8.3.4; extra == 'dev'
